README.txt
setup.cfg
setup.py
collective/__init__.py
collective.media.egg-info/PKG-INFO
collective.media.egg-info/SOURCES.txt
collective.media.egg-info/dependency_links.txt
collective.media.egg-info/entry_points.txt
collective.media.egg-info/namespace_packages.txt
collective.media.egg-info/not-zip-safe
collective.media.egg-info/paster_plugins.txt
collective.media.egg-info/requires.txt
collective.media.egg-info/top_level.txt
collective/media/__init__.py
collective/media/adapters.py
collective/media/configure.zcml
collective/media/events.py
collective/media/indexers.py
collective/media/interfaces.py
collective/media/setuphandlers.py
collective/media/tests.py
collective/media/browser/__init__.py
collective/media/browser/configure.zcml
collective/media/profiles/default/catalog.xml
collective/media/profiles/default/collective_media-default.txt
collective/media/profiles/default/metadata.xml
collective/media/profiles/default/registry.xml
docs/HISTORY.txt
docs/INSTALL.txt
docs/LICENSE.GPL
docs/LICENSE.txt