Metadata-Version: 1.0
Name: collective.media
Version: 0.5
Summary: Adds functionality to retrieve and prioritize media inside of folderish items.
Home-page: http://svn.plone.org/svn/collective/
Author: David Jonas
Author-email: david@intk.com
License: GPL
Keywords: folderish media
Platform: UNKNOWN
Classifier: Framework :: Plone
Classifier: Programming Language :: Python
